cybermarket_server/__init__.py
cybermarket_server/__main__.py
cybermarket_server/cmd_process.py
cybermarket_server/invitation.py
cybermarket_server/lang.py
cybermarket_server/model.py
cybermarket_server/setting.py
cybermarket_server/database/cybermarket.db
cybermarket_server/locale/ru_RU/LC_MESSAGES/Russian.mo
cybermarket_server/locale/zh_CN/LC_MESSAGES/Chinese.mo
cybermarket_server-1.0.1.dist-info/LICENSE
cybermarket_server-1.0.1.dist-info/METADATA
cybermarket_server-1.0.1.dist-info/WHEEL
cybermarket_server-1.0.1.dist-info/top_level.txt
cybermarket_server-1.0.1.dist-info/RECORD
