Metadata-Version: 2.1
Name: cybermarket_server
Version: 1.0.1
Summary: The server of the online network market accepts login, listing, purchase, etc. requests sent by the client.
Author-email: Hailin Liu <0123liuhailin@gmail.com>
License: MIT License
Keywords: shopping,online-market
Classifier: Programming Language :: Python :: 3
Requires-Python: >=3.11
License-File: LICENSE
Requires-Dist: pandas ==2.2.1
Requires-Dist: SQLAlchemy ==2.0.25
